.gitignore
LICENSE
README.md
pyproject.toml
uv.lock
.github/workflows/release.yml
.github/workflows/test.yml
ommx_gurobipy_adapter/__init__.py
ommx_gurobipy_adapter/_version.py
ommx_gurobipy_adapter/adapter.py
ommx_gurobipy_adapter/exception.py
ommx_gurobipy_adapter.egg-info/PKG-INFO
ommx_gurobipy_adapter.egg-info/SOURCES.txt
ommx_gurobipy_adapter.egg-info/dependency_links.txt
ommx_gurobipy_adapter.egg-info/requires.txt
ommx_gurobipy_adapter.egg-info/top_level.txt
tests/test_error.py
tests/test_integration.py
tests/test_ommx_gurobipy.py