Metadata-Version: 2.1
Name: ommx-gurobipy-adapter
Version: 0.2.0rc1
Summary: An adapter for the Gurobipy from/to OMMX.
Author-email: "Jij Inc." <info@j-ij.com>
Project-URL: Repository, https://github.com/Jij-Inc/ommx-gurobipy-adapter
Project-URL: Issues, https://github.com/Jij-Inc/ommx-gurobipy-adapter/issues
Classifier: Programming Language :: Python :: 3 :: Only
Classifier: Programming Language :: Python :: 3.9
Classifier: Programming Language :: Python :: 3.10
Classifier: Programming Language :: Python :: 3.11
Classifier: Programming Language :: Python :: 3.12
Classifier: License :: OSI Approved :: Apache Software License
Requires-Python: >=3.9
License-File: LICENSE
Requires-Dist: gurobipy>=12.0.1
Requires-Dist: ommx<3.0.0,>=2.0.0rc1
